sits/__init__.py
sits/display.py
sits/export.py
sits/indices.py
sits/sits.py
SITS-0.6.1.dist-info/LICENSE
SITS-0.6.1.dist-info/METADATA
SITS-0.6.1.dist-info/WHEEL
SITS-0.6.1.dist-info/top_level.txt
SITS-0.6.1.dist-info/RECORD
