Metadata-Version: 2.1
Name: SITS
Version: 0.6.1
Summary: Get satellite images time series
Home-page: https://github.com/kenoz/SITS_utils
Author: Kenji Ose
Author-email: kenji.ose@ec.europa.eu
Keywords: python,sits,satellite,time series,STAC
Classifier: Development Status :: 3 - Alpha
Classifier: Intended Audience :: Education
Classifier: Programming Language :: Python :: 2
Classifier: Programming Language :: Python :: 3
Classifier: Operating System :: MacOS :: MacOS X
Classifier: Operating System :: Microsoft :: Windows
License-File: LICENSE
Requires-Dist: dask
Requires-Dist: pandas
Requires-Dist: numpy
Requires-Dist: datetime
Requires-Dist: pystac-client
Requires-Dist: pystac ==1.11.0
Requires-Dist: planetary-computer
Requires-Dist: odc-stac
Requires-Dist: odc-geo
Requires-Dist: geopandas
Requires-Dist: rasterio
Requires-Dist: shapely
Requires-Dist: geogif
Requires-Dist: netCDF4
Requires-Dist: spyndex
Provides-Extra: dev
Requires-Dist: dask ; extra == 'dev'
Requires-Dist: pandas ; extra == 'dev'
Requires-Dist: numpy ; extra == 'dev'
Requires-Dist: datetime ; extra == 'dev'
Requires-Dist: pystac-client ; extra == 'dev'
Requires-Dist: pystac ==1.11.0 ; extra == 'dev'
Requires-Dist: planetary-computer ; extra == 'dev'
Requires-Dist: odc-stac ; extra == 'dev'
Requires-Dist: odc-geo ; extra == 'dev'
Requires-Dist: geopandas ; extra == 'dev'
Requires-Dist: rasterio ; extra == 'dev'
Requires-Dist: shapely ; extra == 'dev'
Requires-Dist: geogif ; extra == 'dev'
Requires-Dist: spyndex ; extra == 'dev'
Requires-Dist: sphinx ; extra == 'dev'
Requires-Dist: sphinx-autobuild ; extra == 'dev'
Requires-Dist: sphinx-rtd-theme ; extra == 'dev'
